{"cameraMode":{"drawMode":0,"name":"Shaded","section":"Shading Mode"},"sceneLighting":false,"audioPlay":false,"sceneViewState":{"showFog":true,"showMaterialUpdate":false,"showSkybox":false,"showFlares":true,"showImageEffects":true,"showParticleSystems":true,"showVisualEffectGraphs":true,"m_FxEnabled":true},"in2DMode":false,"pivot":{"x":563.0,"y":430.625,"z":0.0},"rotation":{"x":-0.00539390230551362,"y":-0.9662852883338928,"z":0.26211100816726687,"w":-0.004128315486013889},"size":711.6660766601563,"orthographic":false}